s3serve/__init__.py
s3serve/__main__.py
s3serve/app.py
s3serve/config.py
s3serve/routes/__init__.py
s3serve/routes/buckets.py
s3serve/utils.py
s3serve/web/dist/favicon.ico
s3serve/web/dist/index.html
s3serve/web/eslint.config.js
s3serve/web/index.html
s3serve/web/package.json
s3serve/web/public/favicon.ico
s3serve/web/src/App.tsx
s3serve/web/src/assets/react.svg
s3serve/web/src/components/BucketList.tsx
s3serve/web/src/components/FolderList.tsx
s3serve/web/src/components/ImageObject.style.tsx
s3serve/web/src/components/ImageObject.tsx
s3serve/web/src/components/ObjectGrid.tsx
s3serve/web/src/index.css
s3serve/web/src/main.tsx
s3serve/web/src/utils.ts
s3serve/web/src/vite-env.d.ts
s3serve/web/tsconfig.app.json
s3serve/web/tsconfig.json
s3serve/web/tsconfig.node.json
s3serve/web/vite.config.ts
s3serve/web/yarn.lock
s3serve-0.1.0.dist-info/METADATA
s3serve-0.1.0.dist-info/WHEEL
s3serve-0.1.0.dist-info/entry_points.txt
s3serve-0.1.0.dist-info/RECORD
