Metadata-Version: 2.1
Name: s3serve
Version: 0.1.0
Summary: Simple S3 Server
Author: Rob van der Leek
Author-email: 5324924+robvanderleek@users.noreply.github.com
Requires-Python: >=3.11,<3.14
Classifier: Programming Language :: Python :: 3
Classifier: Programming Language :: Python :: 3.11
Classifier: Programming Language :: Python :: 3.12
Classifier: Programming Language :: Python :: 3.13
Requires-Dist: boto3 (>=1.35.60,<2.0.0)
Requires-Dist: boto3-stubs-lite[s3] (>=1.35.64,<2.0.0)
Requires-Dist: fastapi[standard] (>=0.115.5,<0.116.0)
Requires-Dist: pydantic-settings (>=2.6.1,<3.0.0)
